nobinobi_daily_follow_up/__init__.py
nobinobi_daily_follow_up/admin.py
nobinobi_daily_follow_up/apps.py
nobinobi_daily_follow_up/forms.py
nobinobi_daily_follow_up/menus.py
nobinobi_daily_follow_up/models.py
nobinobi_daily_follow_up/serializers.py
nobinobi_daily_follow_up/signals.py
nobinobi_daily_follow_up/urls.py
nobinobi_daily_follow_up/utils.py
nobinobi_daily_follow_up/views.py
nobinobi_daily_follow_up/widgets.py
nobinobi_daily_follow_up/locale/en/LC_MESSAGES/django.po
nobinobi_daily_follow_up/locale/fr/LC_MESSAGES/django.mo
nobinobi_daily_follow_up/locale/fr/LC_MESSAGES/django.po
nobinobi_daily_follow_up/migrations/0001_initial.py
nobinobi_daily_follow_up/migrations/0001_initial_squashed_0011_auto_20200401_1117.py
nobinobi_daily_follow_up/migrations/0002_auto_20190513_1535.py
nobinobi_daily_follow_up/migrations/0002_auto_20230201_1346.py
nobinobi_daily_follow_up/migrations/0003_add_field_comment_diaperchange.py
nobinobi_daily_follow_up/migrations/0003_troubleshooting.py
nobinobi_daily_follow_up/migrations/0004_auto_20190815_1141.py
nobinobi_daily_follow_up/migrations/0005_auto_20190923_1517.py
nobinobi_daily_follow_up/migrations/0006_medication_child.py
nobinobi_daily_follow_up/migrations/0007_givemedication_date.py
nobinobi_daily_follow_up/migrations/0008_auto_20191021_1443.py
nobinobi_daily_follow_up/migrations/0009_fix_early_troubleshoting_relation.py
nobinobi_daily_follow_up/migrations/0010_add_intermediary_departure_arrival_time.py
nobinobi_daily_follow_up/migrations/0011_auto_20200401_1117.py
nobinobi_daily_follow_up/migrations/__init__.py
nobinobi_daily_follow_up/static/css/nobinobi_daily_follow_up.css
nobinobi_daily_follow_up/static/css/nobinobi_daily_follow_up.css.map
nobinobi_daily_follow_up/static/css/nobinobi_daily_follow_up.scss
nobinobi_daily_follow_up/static/img/.gitignore
nobinobi_daily_follow_up/static/img/smiley/anger.png
nobinobi_daily_follow_up/static/img/smiley/burn.png
nobinobi_daily_follow_up/static/img/smiley/caca.png
nobinobi_daily_follow_up-0.1.2.15.dist-info/AUTHORS.rst
nobinobi_daily_follow_up-0.1.2.15.dist-info/LICENSE
nobinobi_daily_follow_up-0.1.2.15.dist-info/METADATA
nobinobi_daily_follow_up-0.1.2.15.dist-info/WHEEL
nobinobi_daily_follow_up-0.1.2.15.dist-info/top_level.txt
nobinobi_daily_follow_up-0.1.2.15.dist-info/RECORD
