Metadata-Version: 2.1
Name: nobinobi-daily-follow-up
Version: 0.1.2.15
Summary: Application Daily follow-up for nobinobi
Home-page: https://github.com/prolibre-ch/nobinobi-daily-follow-up
Author: Florian Alu
Author-email: alu@prolibre.com
Keywords: nobinobi-daily-follow-up
Classifier: Development Status :: 4 - Beta
Classifier: Framework :: Django :: 3.1
Classifier: Intended Audience :: Developers
Classifier: License :: OSI Approved :: GNU Affero General Public License v3 or later (AGPLv3+)
Classifier: Natural Language :: English
Classifier: Programming Language :: Python :: 3.6
Classifier: Programming Language :: Python :: 3.7
Classifier: Programming Language :: Python :: 3.8
License-File: LICENSE
License-File: AUTHORS.rst
Requires-Dist: nobinobi-child (==0.1.4.25)
Requires-Dist: django-auto-one-to-one (==3.3.5)
Requires-Dist: django-notifications-hq (==1.8.3)
Requires-Dist: drf-writable-nested (==0.7.0)
Requires-Dist: psycopg2-binary (==2.9.9)
Requires-Dist: cffi (==1.16.0)
Requires-Dist: argon2-cffi (==23.1.0)
